MANIFEST.in
README.md
requirements.txt
setup.cfg
setup.py
versioneer.py
LICENSE/LICENSE
LICENSE/LICENSE_LMFIT
docs/sphinx/api.rst
docs/sphinx/first_pass.rst
docs/sphinx/index.rst
docs/sphinx/second_pass.rst
docs/sphinx/theory.rst
pycentroids/__init__.py
pycentroids/_version.py
pycentroids/pycentroids.py
pycentroids.egg-info/PKG-INFO
pycentroids.egg-info/SOURCES.txt
pycentroids.egg-info/dependency_links.txt
pycentroids.egg-info/not-zip-safe
pycentroids.egg-info/requires.txt
pycentroids.egg-info/top_level.txt
pycentroids/tests/__init__.py
pycentroids/tests/test_install.py
pycentroids/tests/test_photons.py