Metadata-Version: 2.1
Name: pycentroids
Version: 0.1.12
Summary: Centroiding algorithms for CCD Single Photon Counting
Home-page: https://github.com/NSLS-II/centroids
Author: Stuart B. Wilkins
Author-email: swilkins@bnl.gov
License: BSD (3-clause)
Platform: UNKNOWN
